gw_fabric_tools/__init__.py
gw_fabric_tools/config.py
gw_fabric_tools/connection.py
gw_fabric_tools/data.py
gw_fabric_tools/deploy.py
gw_fabric_tools/runner.py
gw_fabric_tools-0.1.0.dist-info/METADATA
gw_fabric_tools-0.1.0.dist-info/WHEEL
gw_fabric_tools-0.1.0.dist-info/licenses/LICENSE
gw_fabric_tools-0.1.0.dist-info/RECORD
