Metadata-Version: 2.4
Name: gw-fabric-tools
Version: 0.1.0
Summary: Reusable Fabric tasks for Ghostwing deployments (Docker Compose, backups, data transfer)
Project-URL: Homepage, https://codeberg.org/ghostwing/gw-fabric-tools
Author-email: Ghostwing <yannick@ghostwing.ch>
License: MIT License
License-File: LICENSE
Requires-Python: >=3.10
Requires-Dist: fabric<4,>=2.7
Requires-Dist: invoke<3,>=1.7
